m3_audit/__init__.py
m3_audit/actions.py
m3_audit/db_helpers.py
m3_audit/exceptions.py
m3_audit/helpers.py
m3_audit/manager.py
m3_audit/models.py
m3_audit/ui.py
m3_audit/utils.py
m3_audit/version.py
m3_audit/migrations/0001_initial.py
m3_audit/migrations/__init__.py
m3_audit/south_migrations/0001_initial.py
m3_audit/south_migrations/0002_auto__add_rolesauditmodel.py
m3_audit/south_migrations/__init__.py
m3_audit/templates/m3-audit-list-window.js
m3_audit-2.3.0.dist-info/licenses/LICENSE
tests/__init__.py
tests/manage.py
tests/prepare_env.py
tests/settings.py
tests/shell.sh
tests/test.sh
tests/urls.py
tests/version.py
tests/core/__init__.py
tests/core/tests.py
m3_audit-2.3.0.dist-info/METADATA
m3_audit-2.3.0.dist-info/WHEEL
m3_audit-2.3.0.dist-info/top_level.txt
m3_audit-2.3.0.dist-info/RECORD
