Metadata-Version: 2.4
Name: m3-audit
Version: 2.3.0
Summary: Аудит операций в прикладной системе
Home-page: https://bitbucket.org/barsgroup/m3_audit
Author: BARS Group
Author-email: bars@bars-open.ru
License: MIT
Classifier: Intended Audience :: Developers
Classifier: Environment :: Web Environment
Classifier: Natural Language :: Russian
Classifier: Natural Language :: English
Classifier: Operating System :: OS Independent
Classifier: Programming Language :: Python
Classifier: License :: OSI Approved :: MIT License
Classifier: Development Status :: 5 - Production/Stable
License-File: LICENSE
Requires-Dist: m3_django_compatibility>=1.12.0
Requires-Dist: m3-ui
Requires-Dist: m3-core
Dynamic: author
Dynamic: author-email
Dynamic: classifier
Dynamic: home-page
Dynamic: license
Dynamic: license-file
Dynamic: requires-dist
Dynamic: summary
